accounts/__init__.py
accounts/admin.py
accounts/apps.py
accounts/backend.py
accounts/constants.py
accounts/models.py
accounts/serializers.py
accounts/tests.py
accounts/urls.py
accounts/views.py
accounts/migrations/0001_initial.py
accounts/migrations/__init__.py
ns_django_custom_auth-0.2.dist-info/METADATA
ns_django_custom_auth-0.2.dist-info/WHEEL
ns_django_custom_auth-0.2.dist-info/top_level.txt
ns_django_custom_auth-0.2.dist-info/RECORD
